{
  "id": 673663144,
  "node_id": "R_kgDOKCdIqA",
  "name": "companion-app",
  "full_name": "rahul/companion-app",
  "private": false,
  "owner": {
    "login": "rahul",
    "id": 858220,
    "node_id": "MDQ6VXNlcjg1ODIyMA==",
    "avatar_url": "https://avatars.githubusercontent.com/u/858220?v=4",
    "gravatar_id": "",
    "url": "https://api.github.com/users/rahul",
    "html_url": "https://github.com/rahul",
    "followers_url": "https://api.github.com/users/rahul/followers",
    "following_url": "https://api.github.com/users/rahul/following{/other_user}",
    "gists_url": "https://api.github.com/users/rahul/gists{/gist_id}",
    "starred_url": "https://api.github.com/users/rahul/starred{/owner}{/repo}",
    "subscriptions_url": "https://api.github.com/users/rahul/subscriptions",
    "organizations_url": "https://api.github.com/users/rahul/orgs",
    "repos_url": "https://api.github.com/users/rahul/repos",
    "events_url": "https://api.github.com/users/rahul/events{/privacy}",
    "received_events_url": "https://api.github.com/users/rahul/received_events",
    "type": "User",
    "site_admin": false
  },
  "html_url": "https://github.com/rahul/companion-app",
  "description": "AI companions with memory: a lightweight stack to create and host your own AI companions",
  "fork": true,
  "url": "https://api.github.com/repos/rahul/companion-app",
  "forks_url": "https://api.github.com/repos/rahul/companion-app/forks",
  "keys_url": "https://api.github.com/repos/rahul/companion-app/keys{/key_id}",
  "collaborators_url": "https://api.github.com/repos/rahul/companion-app/collaborators{/collaborator}",
  "teams_url": "https://api.github.com/repos/rahul/companion-app/teams",
  "hooks_url": "https://api.github.com/repos/rahul/companion-app/hooks",
  "issue_events_url": "https://api.github.com/repos/rahul/companion-app/issues/events{/number}",
  "events_url": "https://api.github.com/repos/rahul/companion-app/events",
  "assignees_url": "https://api.github.com/repos/rahul/companion-app/assignees{/user}",
  "branches_url": "https://api.github.com/repos/rahul/companion-app/branches{/branch}",
  "tags_url": "https://api.github.com/repos/rahul/companion-app/tags",
  "blobs_url": "https://api.github.com/repos/rahul/companion-app/git/blobs{/sha}",
  "git_tags_url": "https://api.github.com/repos/rahul/companion-app/git/tags{/sha}",
  "git_refs_url": "https://api.github.com/repos/rahul/companion-app/git/refs{/sha}",
  "trees_url": "https://api.github.com/repos/rahul/companion-app/git/trees{/sha}",
  "statuses_url": "https://api.github.com/repos/rahul/companion-app/statuses/{sha}",
  "languages_url": "https://api.github.com/repos/rahul/companion-app/languages",
  "stargazers_url": "https://api.github.com/repos/rahul/companion-app/stargazers",
  "contributors_url": "https://api.github.com/repos/rahul/companion-app/contributors",
  "subscribers_url": "https://api.github.com/repos/rahul/companion-app/subscribers",
  "subscription_url": "https://api.github.com/repos/rahul/companion-app/subscription",
  "commits_url": "https://api.github.com/repos/rahul/companion-app/commits{/sha}",
  "git_commits_url": "https://api.github.com/repos/rahul/companion-app/git/commits{/sha}",
  "comments_url": "https://api.github.com/repos/rahul/companion-app/comments{/number}",
  "issue_comment_url": "https://api.github.com/repos/rahul/companion-app/issues/comments{/number}",
  "contents_url": "https://api.github.com/repos/rahul/companion-app/contents/{+path}",
  "compare_url": "https://api.github.com/repos/rahul/companion-app/compare/{base}...{head}",
  "merges_url": "https://api.github.com/repos/rahul/companion-app/merges",
  "archive_url": "https://api.github.com/repos/rahul/companion-app/{archive_format}{/ref}",
  "downloads_url": "https://api.github.com/repos/rahul/companion-app/downloads",
  "issues_url": "https://api.github.com/repos/rahul/companion-app/issues{/number}",
  "pulls_url": "https://api.github.com/repos/rahul/companion-app/pulls{/number}",
  "milestones_url": "https://api.github.com/repos/rahul/companion-app/milestones{/number}",
  "notifications_url": "https://api.github.com/repos/rahul/companion-app/notifications{?since,all,participating}",
  "labels_url": "https://api.github.com/repos/rahul/companion-app/labels{/name}",
  "releases_url": "https://api.github.com/repos/rahul/companion-app/releases{/id}",
  "deployments_url": "https://api.github.com/repos/rahul/companion-app/deployments",
  "created_at": "2023-08-02T06:29:34Z",
  "updated_at": "2023-08-02T06:29:34Z",
  "pushed_at": "2023-07-31T15:14:00Z",
  "git_url": "git://github.com/rahul/companion-app.git",
  "ssh_url": "git@github.com:rahul/companion-app.git",
  "clone_url": "https://github.com/rahul/companion-app.git",
  "svn_url": "https://github.com/rahul/companion-app",
  "homepage": "https://ai-companion-stack.com/",
  "size": 4902,
  "stargazers_count": 0,
  "watchers_count": 0,
  "language": null,
  "has_issues": false,
  "has_projects": true,
  "has_downloads": true,
  "has_wiki": true,
  "has_pages": false,
  "has_discussions": false,
  "forks_count": 0,
  "mirror_url": null,
  "archived": false,
  "disabled": false,
  "open_issues_count": 0,
  "license": {
    "key": "mit",
    "name": "MIT License",
    "spdx_id": "MIT",
    "url": "https://api.github.com/licenses/mit",
    "node_id": "MDc6TGljZW5zZTEz"
  },
  "allow_forking": true,
  "is_template": false,
  "web_commit_signoff_required": false,
  "topics": [],
  "visibility": "public",
  "forks": 0,
  "open_issues": 0,
  "watchers": 0,
  "default_branch": "main"
}
